filez4eva/__init__.py
filez4eva/__main__.py
filez4eva/command/__init__.py
filez4eva/command/scan_dir_command.py
filez4eva/command/stow_file_command.py
filez4eva/error.py
filez4eva-3.0.13.dist-info/METADATA
filez4eva-3.0.13.dist-info/WHEEL
filez4eva-3.0.13.dist-info/entry_points.txt
filez4eva-3.0.13.dist-info/RECORD
