Metadata-Version: 2.3
Name: filez4eva
Version: 3.0.13
Summary: Shift scans, photos, and other files into structured folders for permanent safekeeping
License: MIT
Author: Steampunk Wizard
Author-email: filez4eva@steamwiz.io
Requires-Python: >=3.11,<3.12
Classifier: License :: OSI Approved :: MIT License
Classifier: Programming Language :: Python :: 3
Classifier: Programming Language :: Python :: 3.11
Requires-Dist: watchdog (>=3.0.0,<4.0.0)
Requires-Dist: wizlib (>=3.1.1,<4.0.0)
Project-URL: Homepage, https://steamwiz.io
Project-URL: Repository, https://gitlab.com/steamwiz/filez4eva
